xy_argparse/ArgParse.py
xy_argparse/ModuleData.py
xy_argparse/Resource.py
xy_argparse/Runner.py
xy_argparse/__init__.py
xy_argparse/execute/Main.py
xy_argparse/execute/__init__.py
xy_argparse-1.0.12.dist-info/licenses/LICENSE
xy_argparse-1.0.12.dist-info/METADATA
xy_argparse-1.0.12.dist-info/WHEEL
xy_argparse-1.0.12.dist-info/top_level.txt
xy_argparse-1.0.12.dist-info/RECORD
