Metadata-Version: 2.4
Name: xy_argparse
Version: 1.0.12
Summary: xy_argparse 模块
Author-email: 余洋 <yuyangit.0515@qq.com>
Classifier: Programming Language :: Python :: 3.8
Requires-Python: >=3.8
License-File: LICENSE
Requires-Dist: setuptools
Requires-Dist: wheel
Dynamic: license-file
